LICENSE.txt
README.md
setup.py
setyp.cfg
gmm_uniform/GMM.py
gmm_uniform/__init__.py
gmm_uniform.egg-info/PKG-INFO
gmm_uniform.egg-info/SOURCES.txt
gmm_uniform.egg-info/dependency_links.txt
gmm_uniform.egg-info/requires.txt
gmm_uniform.egg-info/top_level.txt