Metadata-Version: 2.1
Name: gmm-uniform
Version: 0.0.3
Summary: Gaussian mixture models with uniform noise
Home-page: https://github.com/nassim199/GMM-Project
Download-URL: https://github.com/nassim199/GMM-Project/archive/refs/tags/0.0.1.tar.gz
Author: Nassim Hammadou, Khdoja Tayeb Mounir
Author-email: hammadounassim0@gmail.com
License: GPL-3.0
Project-URL: Bug Tracker, https://github.com/nassim199/GMM-Project/issues
Keywords: pypi,gmm_uniform,mixture models
Classifier: Development Status :: 3 - Alpha
Classifier: Intended Audience :: Developers
Classifier: Topic :: Software Development :: Documentation
Classifier: License :: OSI Approved :: GNU General Public License v3 (GPLv3)
Classifier: Programming Language :: Python :: 3
Classifier: Programming Language :: Python :: 3.7
Classifier: Programming Language :: Python :: 3.8
Classifier: Programming Language :: Python :: 3.9
License-File: LICENSE.txt
